{"frames":[{"filename":"idle0000","frame":{"x":81,"y":72,"w":33,"h":56},"rotated":false,"trimmed":false,"spriteSourceSize":{"x":0,"y":0,"w":33,"h":56},"sourceSize":{"w":33,"h":56}},{"filename":"idle0001","frame":{"x":281,"y":72,"w":33,"h":56},"rotated":false,"trimmed":false,"spriteSourceSize":{"x":0,"y":0,"w":33,"h":56},"sourceSize":{"w":33,"h":56}},{"filename":"idle0002","frame":{"x":481,"y":72,"w":33,"h":56},"rotated":false,"trimmed":false,"spriteSourceSize":{"x":0,"y":0,"w":33,"h":54},"sourceSize":{"w":33,"h":54}},{"filename":"idle0003","frame":{"x":681,"y":72,"w":33,"h":56},"rotated":false,"trimmed":false,"spriteSourceSize":{"x":0,"y":0,"w":33,"h":54},"sourceSize":{"w":33,"h":54}}],"meta":{"app":"https://www.leshylabs.com/apps/sstool/","version":"Leshy SpriteSheet Tool v0.8.4","image":"ninja_idle.png","size":{"w":800,"h":200},"scale":1}}